dsvisualizer/__init__.py
dsvisualizer/_frontend.py
dsvisualizer/_version.py
dsvisualizer/logger.py
dsvisualizer/magic.py
dsvisualizer/operations.py
dsvisualizer/traits.py
dsvisualizer/widget.py
dsvisualizer/labextension/package.json
dsvisualizer/labextension/static/12.a1d5ce55b37cce5a2096.js
dsvisualizer/labextension/static/216.8713f8b686c13a482824.js
dsvisualizer/labextension/static/480.6e3f688db471ec6543b6.js
dsvisualizer/labextension/static/568.98cca6cf4049527fd8f2.js
dsvisualizer/labextension/static/remoteEntry.7d81850165b9be37e0f0.js
dsvisualizer/labextension/static/style.js
dsvisualizer/labextension/static/third-party-licenses.json
dsvisualizer/nbextension/extension.js
dsvisualizer/nbextension/index.js
dsvisualizer/nbextension/index.js.map
dsvisualizer/tests/__init__.py
dsvisualizer/tests/conftest.py
dsvisualizer/tests/test_magic.py
dsvisualizer/tests/test_nbextension_path.py
dsvisualizer/tests/test_operation.py
dsvisualizer/tests/test_traits.py
dsvisualizer-0.1.7.dev0.data/data/etc/jupyter/nbconfig/notebook.d/dsvisualizer.json
dsvisualizer-0.1.7.dev0.data/data/share/jupyter/labextensions/dsvisualizer/install.json
dsvisualizer-0.1.7.dev0.data/data/share/jupyter/labextensions/dsvisualizer/package.json
dsvisualizer-0.1.7.dev0.data/data/share/jupyter/labextensions/dsvisualizer/static/12.a1d5ce55b37cce5a2096.js
dsvisualizer-0.1.7.dev0.data/data/share/jupyter/labextensions/dsvisualizer/static/216.8713f8b686c13a482824.js
dsvisualizer-0.1.7.dev0.data/data/share/jupyter/labextensions/dsvisualizer/static/480.6e3f688db471ec6543b6.js
dsvisualizer-0.1.7.dev0.data/data/share/jupyter/labextensions/dsvisualizer/static/568.98cca6cf4049527fd8f2.js
dsvisualizer-0.1.7.dev0.data/data/share/jupyter/labextensions/dsvisualizer/static/remoteEntry.7d81850165b9be37e0f0.js
dsvisualizer-0.1.7.dev0.data/data/share/jupyter/labextensions/dsvisualizer/static/style.js
dsvisualizer-0.1.7.dev0.data/data/share/jupyter/labextensions/dsvisualizer/static/third-party-licenses.json
dsvisualizer-0.1.7.dev0.dist-info/LICENSE.txt
dsvisualizer-0.1.7.dev0.dist-info/METADATA
dsvisualizer-0.1.7.dev0.dist-info/WHEEL
dsvisualizer-0.1.7.dev0.dist-info/top_level.txt
dsvisualizer-0.1.7.dev0.dist-info/RECORD
